{
    "organism": "yeast",
    "total_features": 26,
    "total_triplets": 9,
    "all_features_covered": true,
    "features_covered_count": 26,
    "triplets": [
        {
            "triplet_id": 1,
            "feature1": "H3K9ac",
            "feature2": "H3K4me",
            "feature3": "H4K5ac"
        },
        {
            "triplet_id": 2,
            "feature1": "H4R3me",
            "feature2": "H3K4me3",
            "feature3": "H3K56ac"
        },
        {
            "triplet_id": 3,
            "feature1": "Htz1",
            "feature2": "H4K12ac",
            "feature3": "H4R3me2s"
        },
        {
            "triplet_id": 4,
            "feature1": "H3K14ac",
            "feature2": "H4K8ac",
            "feature3": "H3K4me2"
        },
        {
            "triplet_id": 5,
            "feature1": "H3S10ph",
            "feature2": "H3K4ac",
            "feature3": "H3K23ac"
        },
        {
            "triplet_id": 6,
            "feature1": "H3K79me3",
            "feature2": "H4K20me",
            "feature3": "H3K36me3"
        },
        {
            "triplet_id": 7,
            "feature1": "H3K36me",
            "feature2": "H2AS129ph",
            "feature3": "H4K16ac"
        },
        {
            "triplet_id": 8,
            "feature1": "H3K18ac",
            "feature2": "H3K27ac",
            "feature3": "H3K79me"
        },
        {
            "triplet_id": 9,
            "feature1": "H3K36me2",
            "feature2": "H2AK5ac",
            "feature3": "H3K4me2"
        }
    ]
}